package com.google.android.gms.internal;

class cp$1
  implements Runnable
{
  // ERROR //
  public void run()
  {
    // Byte code:
    //   0: aload_0
    //   1: getfield 19	com/google/android/gms/internal/cp$1:qw	Lcom/google/android/gms/internal/cp;
    //   4: invokestatic 29	com/google/android/gms/internal/cp:a	(Lcom/google/android/gms/internal/cp;)Ljava/lang/Object;
    //   7: astore_1
    //   8: aload_1
    //   9: monitorenter
    //   10: aload_0
    //   11: getfield 19	com/google/android/gms/internal/cp$1:qw	Lcom/google/android/gms/internal/cp;
    //   14: invokestatic 32	com/google/android/gms/internal/cp:b	(Lcom/google/android/gms/internal/cp;)I
    //   17: bipush 254
    //   19: if_icmpeq +8 -> 27
    //   22: aload_1
    //   23: monitorexit
    //   24: goto +70 -> 94
    //   27: aload_0
    //   28: getfield 19	com/google/android/gms/internal/cp$1:qw	Lcom/google/android/gms/internal/cp;
    //   31: aload_0
    //   32: getfield 19	com/google/android/gms/internal/cp$1:qw	Lcom/google/android/gms/internal/cp;
    //   35: invokestatic 36	com/google/android/gms/internal/cp:c	(Lcom/google/android/gms/internal/cp;)Lcom/google/android/gms/internal/cu;
    //   38: invokestatic 39	com/google/android/gms/internal/cp:a	(Lcom/google/android/gms/internal/cp;Lcom/google/android/gms/internal/cu;)Lcom/google/android/gms/internal/cu;
    //   41: pop
    //   42: aload_0
    //   43: getfield 19	com/google/android/gms/internal/cp$1:qw	Lcom/google/android/gms/internal/cp;
    //   46: invokestatic 42	com/google/android/gms/internal/cp:d	(Lcom/google/android/gms/internal/cp;)Lcom/google/android/gms/internal/cu;
    //   49: ifnonnull +21 -> 70
    //   52: aload_0
    //   53: getfield 19	com/google/android/gms/internal/cp$1:qw	Lcom/google/android/gms/internal/cp;
    //   56: iconst_4
    //   57: invokevirtual 46	com/google/android/gms/internal/cp:j	(I)V
    //   60: aload_1
    //   61: monitorexit
    //   62: goto +32 -> 94
    //   65: astore_2
    //   66: aload_1
    //   67: monitorexit
    //   68: aload_2
    //   69: athrow
    //   70: aload_0
    //   71: getfield 21	com/google/android/gms/internal/cp$1:qv	Lcom/google/android/gms/internal/co;
    //   74: aload_0
    //   75: getfield 19	com/google/android/gms/internal/cp$1:qw	Lcom/google/android/gms/internal/cp;
    //   78: invokevirtual 51	com/google/android/gms/internal/co:a	(Lcom/google/android/gms/internal/cq$a;)V
    //   81: aload_0
    //   82: getfield 19	com/google/android/gms/internal/cp$1:qw	Lcom/google/android/gms/internal/cp;
    //   85: aload_0
    //   86: getfield 21	com/google/android/gms/internal/cp$1:qv	Lcom/google/android/gms/internal/co;
    //   89: invokestatic 53	com/google/android/gms/internal/cp:a	(Lcom/google/android/gms/internal/cp;Lcom/google/android/gms/internal/co;)V
    //   92: aload_1
    //   93: monitorexit
    //   94: return
    //
    // Exception table:
    //   from	to	target	type
    //   10	68	65	finally
    //   70	94	65	finally
  }
}

/* Location:           C:\Users\Lino\java\2014\APKtoJava_RC2\tools\classes-dex2jar.jar
 * Qualified Name:     com.google.android.gms.internal.cp.1
 * JD-Core Version:    0.6.0
 */