package com.google.android.gms.internal;

class fe$3
  implements Runnable
{
  // ERROR //
  public void run()
  {
    // Byte code:
    //   0: aload_0
    //   1: getfield 17	com/google/android/gms/internal/fe$3:tr	Lcom/google/android/gms/internal/fe;
    //   4: invokestatic 25	com/google/android/gms/internal/fe:a	(Lcom/google/android/gms/internal/fe;)Ljava/lang/Object;
    //   7: astore_1
    //   8: aload_1
    //   9: monitorenter
    //   10: aload_0
    //   11: getfield 17	com/google/android/gms/internal/fe$3:tr	Lcom/google/android/gms/internal/fe;
    //   14: invokestatic 29	com/google/android/gms/internal/fe:c	(Lcom/google/android/gms/internal/fe;)Lcom/google/android/gms/internal/fk;
    //   17: getfield 35	com/google/android/gms/internal/fk:errorCode	I
    //   20: bipush 254
    //   22: if_icmpeq +8 -> 30
    //   25: aload_1
    //   26: monitorexit
    //   27: goto +142 -> 169
    //   30: aload_0
    //   31: getfield 17	com/google/android/gms/internal/fe$3:tr	Lcom/google/android/gms/internal/fe;
    //   34: invokestatic 39	com/google/android/gms/internal/fe:d	(Lcom/google/android/gms/internal/fe;)Lcom/google/android/gms/internal/gv;
    //   37: invokevirtual 45	com/google/android/gms/internal/gv:dv	()Lcom/google/android/gms/internal/gw;
    //   40: aload_0
    //   41: getfield 17	com/google/android/gms/internal/fe$3:tr	Lcom/google/android/gms/internal/fe;
    //   44: invokevirtual 50	com/google/android/gms/internal/gw:a	(Lcom/google/android/gms/internal/gw$a;)V
    //   47: aload_0
    //   48: getfield 17	com/google/android/gms/internal/fe$3:tr	Lcom/google/android/gms/internal/fe;
    //   51: invokestatic 29	com/google/android/gms/internal/fe:c	(Lcom/google/android/gms/internal/fe;)Lcom/google/android/gms/internal/fk;
    //   54: getfield 35	com/google/android/gms/internal/fk:errorCode	I
    //   57: bipush 253
    //   59: if_icmpne +64 -> 123
    //   62: new 52	java/lang/StringBuilder
    //   65: dup
    //   66: invokespecial 53	java/lang/StringBuilder:<init>	()V
    //   69: ldc 55
    //   71: invokevirtual 59	java/lang/StringBuilder:append	(Ljava/lang/String;)Ljava/lang/StringBuilder;
    //   74: aload_0
    //   75: getfield 17	com/google/android/gms/internal/fe$3:tr	Lcom/google/android/gms/internal/fe;
    //   78: invokestatic 29	com/google/android/gms/internal/fe:c	(Lcom/google/android/gms/internal/fe;)Lcom/google/android/gms/internal/fk;
    //   81: getfield 63	com/google/android/gms/internal/fk:rP	Ljava/lang/String;
    //   84: invokevirtual 59	java/lang/StringBuilder:append	(Ljava/lang/String;)Ljava/lang/StringBuilder;
    //   87: invokevirtual 67	java/lang/StringBuilder:toString	()Ljava/lang/String;
    //   90: invokestatic 73	com/google/android/gms/internal/gs:V	(Ljava/lang/String;)V
    //   93: aload_0
    //   94: getfield 17	com/google/android/gms/internal/fe$3:tr	Lcom/google/android/gms/internal/fe;
    //   97: invokestatic 39	com/google/android/gms/internal/fe:d	(Lcom/google/android/gms/internal/fe;)Lcom/google/android/gms/internal/gv;
    //   100: aload_0
    //   101: getfield 17	com/google/android/gms/internal/fe$3:tr	Lcom/google/android/gms/internal/fe;
    //   104: invokestatic 29	com/google/android/gms/internal/fe:c	(Lcom/google/android/gms/internal/fe;)Lcom/google/android/gms/internal/fk;
    //   107: getfield 63	com/google/android/gms/internal/fk:rP	Ljava/lang/String;
    //   110: invokevirtual 76	com/google/android/gms/internal/gv:loadUrl	(Ljava/lang/String;)V
    //   113: aload_1
    //   114: monitorexit
    //   115: goto +54 -> 169
    //   118: astore_2
    //   119: aload_1
    //   120: monitorexit
    //   121: aload_2
    //   122: athrow
    //   123: ldc 78
    //   125: invokestatic 73	com/google/android/gms/internal/gs:V	(Ljava/lang/String;)V
    //   128: aload_0
    //   129: getfield 17	com/google/android/gms/internal/fe$3:tr	Lcom/google/android/gms/internal/fe;
    //   132: invokestatic 39	com/google/android/gms/internal/fe:d	(Lcom/google/android/gms/internal/fe;)Lcom/google/android/gms/internal/gv;
    //   135: aload_0
    //   136: getfield 17	com/google/android/gms/internal/fe$3:tr	Lcom/google/android/gms/internal/fe;
    //   139: invokestatic 29	com/google/android/gms/internal/fe:c	(Lcom/google/android/gms/internal/fe;)Lcom/google/android/gms/internal/fk;
    //   142: getfield 63	com/google/android/gms/internal/fk:rP	Ljava/lang/String;
    //   145: invokestatic 84	com/google/android/gms/internal/gj:L	(Ljava/lang/String;)Ljava/lang/String;
    //   148: aload_0
    //   149: getfield 17	com/google/android/gms/internal/fe$3:tr	Lcom/google/android/gms/internal/fe;
    //   152: invokestatic 29	com/google/android/gms/internal/fe:c	(Lcom/google/android/gms/internal/fe;)Lcom/google/android/gms/internal/fk;
    //   155: getfield 87	com/google/android/gms/internal/fk:tG	Ljava/lang/String;
    //   158: ldc 89
    //   160: ldc 91
    //   162: aconst_null
    //   163: invokevirtual 95	com/google/android/gms/internal/gv:loadDataWithBaseURL	(Ljava/lang/String;Ljava/lang/String;Ljava/lang/String;Ljava/lang/String;Ljava/lang/String;)V
    //   166: goto -53 -> 113
    //   169: return
    //
    // Exception table:
    //   from	to	target	type
    //   10	121	118	finally
    //   123	166	118	finally
  }
}

/* Location:           C:\Users\Lino\java\2014\APKtoJava_RC2\tools\classes-dex2jar.jar
 * Qualified Name:     com.google.android.gms.internal.fe.3
 * JD-Core Version:    0.6.0
 */